opendata/__init__.py
opendata/conf.py
opendata/main.py
opendata/mixins.py
opendata/models.py
opendata/utils.py
goldencheetah_opendata-0.3.1.dist-info/LICENSE
goldencheetah_opendata-0.3.1.dist-info/METADATA
goldencheetah_opendata-0.3.1.dist-info/WHEEL
goldencheetah_opendata-0.3.1.dist-info/top_level.txt
goldencheetah_opendata-0.3.1.dist-info/RECORD
